examples/__init__.py
examples/app_rest_crud_test.py
examples/rest_app_quitckstart.py
examples/crud/__init__.py
examples/crud/rest_app_test.py
examples/crud/controller/__init__.py
examples/crud/controller/person_controller.py
examples/crud/dto/__init__.py
examples/crud/dto/person_dto.py
examples/crud/model/__init__.py
examples/crud/model/person.py
examples/crud/service/__init__.py
examples/crud/service/person_service.py
examples/form/__init__.py
examples/form/form_app_test.py
examples/form/person/__init__.py
examples/form/person/person.py
examples/form/person/person_blueprint.py
examples/form/person/person_form.py
pf_flask_rest/__init__.py
pf_flask_rest/pf_flask_request_processor.py
pf_flask_rest/pf_flask_response_processor.py
pf_flask_rest/pf_flask_rest.py
pf_flask_rest/api/__init__.py
pf_flask_rest/api/pf_app_api_def.py
pf_flask_rest/common/__init__.py
pf_flask_rest/common/pf_flask_rest_config.py
pf_flask_rest/common/pffr_exception_handler.py
pf_flask_rest/form/__init__.py
pf_flask_rest/form/pf_app_form_def.py
pf_flask_rest/form/common/__init__.py
pf_flask_rest/form/common/pffr_field_data.py
pf_flask_rest/form/common/pffr_form_action.py
pf_flask_rest/form/common/pffr_form_definition.py
pf_flask_rest/helper/__init__.py
pf_flask_rest/helper/pf_flask_crud_helper.py
pf_flask_rest/helper/pf_flask_form_crud_helper.py
pf_flask_rest/helper/pf_flask_rest_crud_helper.py
PF_Flask_REST-1.0.1.dist-info/LICENSE
PF_Flask_REST-1.0.1.dist-info/METADATA
PF_Flask_REST-1.0.1.dist-info/WHEEL
PF_Flask_REST-1.0.1.dist-info/top_level.txt
PF_Flask_REST-1.0.1.dist-info/RECORD
